{"relation": [["", "-", "-", "-", "-", "-", "-", "-", "-", "-", "-", "-", "-", "-", "-", "-", "-", "-", "-", "-", "-", "-", "-", "-", "-", "-", "-", "-", "-", "-", "-", "-"], ["Discussion Topic", "Since we're on DU.....", "what about a Christian Democratic Party of America?", "For a good laugh...", "Heheh Check out the note a freeper left in my guestbook, and my reply.", "Does anyone know anyplace I can find a list of differences", "This has become a second \"safe forum\" for me", "Thought my liberal Christian friends would get a kick out of this...", "What feeds your soul? [View All]", "Did anyone else hear the prayer service on Friday, 1/ 21?", "A special outreach to (and a Hug for) the Christian Liberals DU Group ..", "Why aren't we speaking out? -- DU post", "Liberal Christian/Faith Reading:", "I'm getting a new study Bible. I've never looked at it in person but", "Prayer requests", "Prayer request, emergency in my city...", "Just for Fun", "RevCheesehead; I'm curious about what you did regarding your problem...", "If anyone has a need to purchase religious jewelry, this site..", "Megachurches", "What is your church doing to help the Tsunami victims?", "Ugh...feel free to alert these threads to the mods...", "As always, let me know what good stuff I am missing from my website.", "The Sunday sermon I didn't hear.", "I have a question about Episcopal Church Governance", "Which churches have started having consciencious objector meetings?", "Women in ministry- some info...", "Dr. Robin Meyers' Speech to students at OK University", "Let's get this party started... [View All]", "I need help with a problem.", "Kerry Mideast trip prayer thread", "Today is World Peace Day"], ["Author", "boomboom", "pres2032", "melnjones", "GreenPartyVot...", "shawn703", "realisticphis...", "Frogtutor", "RevCheesehead", "CBHagman", "Maat", "AngryOldDem", "GreenPartyVot...", "GreenPartyVot...", "GreenPartyVot...", "melnjones", "mourningdove9...", "Frogtutor", "Princess Tura...", "kwassa", "cally", "melnjones", "GreenPartyVot...", "Imalittleteap...", "AlabamaYankee", "genius", "melnjones", "melnjones", "boomboom", "RevCheesehead", "LittleClarkie", "Cuban_Liberal"], ["Start time | Last reply", "Sat Jan-29-05 09:00 AM", "Fri Jan-28-05 07:54 PM", "Fri Jan-28-05 06:07 PM", "Thu Jan-27-05 10:17 PM", "Thu Jan-27-05 09:12 AM", "Thu Jan-27-05 01:52 AM", "Tue Jan-25-05 02:18 PM", "Sun Jan-23-05 05:51 PM", "Sat Jan-22-05 07:19 PM", "Sat Jan-22-05 06:57 PM", "Sat Jan-22-05 12:29 PM", "Wed Jan-19-05 06:48 AM", "Wed Jan-19-05 06:41 AM", "Mon Jan-17-05 09:51 PM", "Mon Jan-17-05 04:34 PM", "Sun Jan-16-05 12:07 AM", "Sat Jan-15-05 12:26 PM", "Sat Jan-15-05 01:38 AM", "Fri Jan-14-05 10:23 PM", "Fri Jan-14-05 02:50 PM", "Fri Jan-14-05 01:53 PM", "Thu Jan-13-05 12:07 PM", "Thu Jan-13-05 07:56 AM", "Wed Jan-12-05 11:52 AM", "Mon Jan-10-05 06:52 PM", "Mon Jan-10-05 05:43 PM", "Sun Jan-09-05 12:28 PM", "Fri Jan-07-05 09:25 PM", "Thu Jan-06-05 04:55 PM", "Tue Jan-04-05 09:38 PM", "Sat Jan-01-05 09:54 PM"], ["Replies", "5", "2", "2", "3", "2", "8", "4", "21", "0", "16", "19", "7", "4", "1", "2", "1", "2", "1", "7", "13", "15", "0", "1", "9", "1", "4", "0", "29", "10", "10", "3"], ["Recs", "0", "0", "0", "0", "0", "0", "0", "0", "0", "0", "0", "0", "0", "0", "0", "0", "0", "0", "0", "0", "0", "0", "0", "0", "0", "0", "0", "0", "0", "0", "0"]], "pageTitle": "Democratic Underground - Christian Liberals/Progressive People of Faith Group", "title": "", "url": "http://www.democraticunderground.com/discuss/duboard.php?az=show_topics&forum=291&page=11", "hasHeader": true, "headerPosition": "FIRST_ROW", "tableType": "RELATION", "tableNum": 4, "s3Link": "common-crawl/crawl-data/CC-MAIN-2015-32/segments/1438042987127.36/warc/CC-MAIN-20150728002307-00261-ip-10-236-191-2.ec2.internal.warc.gz", "recordEndOffset": 405100155, "recordOffset": 405092320, "tableOrientation": "HORIZONTAL", "TableContextTimeStampAfterTable": "{26862=Powered by DCForum+ Version 1.1 Copyright 1997-2002 DCScripts.com Software has been extensively modified by the DU administrators, 28398=\u00a9 2001 - 2011 Democratic Underground, LLC}", "textBeforeTable": "GA_googleFillSlot(\"DU2_Forum_Leaderboard_Top\");", "textAfterTable": "Page 1 | ... | 5 | 6 | 7 | 8 | 9 | 10 | 11|\u00a0Archives Big Forums \u00a0\u00a0|-- Latest Breaking News \u00a0\u00a0|-- Editorials & Other Articles \u00a0\u00a0|-- Political Videos \u00a0\u00a0|-- General Discussion \u00a0\u00a0|-- General Discussion: Presidency \u00a0\u00a0|-- The DU Lounge \u00a0\u00a0|-- Ask the Administrators Forum Categories \u00a0\u00a0|-- Topic Forums \u00a0\u00a0|-- Places \u00a0\u00a0|-- DU Groups \u00a0\u00a0|-- Archives My Forums Home \u00bb Discuss\u00a0\u00bb DU Groups\u00a0\u00bb\u00a0Religion & Spirituality\u00a0\u00bb\u00a0Christian Liberals/Progressive People of Faith Group\u00a0| Add to My Forums [?] Powered by DCForum+ Version 1.1 Copyright 1997-2002 DCScripts.com Software has been extensively modified by the DU administrators Important Notices: By participating on this discussion board, visitors agree to abide by the rules outlined on our Rules page. Messages posted", "hasKeyColumn": true, "keyColumnIndex": 1, "headerRowIndex": 0}