{"relation": [["", "1", "2", "3", "4", "5", "6", "7", "8", "9", "10"], ["Name", "ExplicitLive Your Life (feat. Rihanna)", "ExplicitWhatever You Like", "ExplicitDead and Gone (feat. Justin Timberlake)", "ExplicitWhat You Know", "CleanLive Your Life (feat. Rihanna)", "CleanDead and Gone (feat. Justin Timberlake)", "ExplicitHello Good Morning (feat. T.I.)", "CleanWhatever You Like", "ExplicitBring Em Out", "ExplicitThat's All She Wrote (feat. Eminem)"], ["Album", "Paper Trail (Deluxe Version)", "Paper Trail (Deluxe Version)", "Paper Trail (Deluxe Version)", "King", "Paper Trail (Deluxe Version)", "Paper Trail (Deluxe Version)", "Last Train to Paris (Deluxe Version)", "Paper Trail (Deluxe Version)", "Urban Legend", "No Mercy (Deluxe Version)"], ["Time", "5:38", "4:09", "4:59", "4:33", "5:38", "4:59", "4:28", "4:09", "3:38", "5:18"], ["Price", "$1.29", "$1.29", "$1.29", "$1.29", "$1.29", "$1.29", "$1.29", "$1.29", "$1.29", "$1.29"], ["", "View In iTunes", "View In iTunes", "View In iTunes", "View In iTunes", "View In iTunes", "View In iTunes", "View In iTunes", "View In iTunes", "View In iTunes", "View In iTunes"]], "pageTitle": "iTunes - Music - Trouble Man: Heavy Is the Head by T.I.", "title": "", "url": "https://itunes.apple.com/us/album/trouble-man-heavy-is-the-head/id585938420", "hasHeader": true, "headerPosition": "FIRST_ROW", "tableType": "RELATION", "tableNum": 2, "s3Link": "common-crawl/crawl-data/CC-MAIN-2015-32/segments/1438042988458.74/warc/CC-MAIN-20150728002308-00285-ip-10-236-191-2.ec2.internal.warc.gz", "recordEndOffset": 868897115, "recordOffset": 868867300, "tableOrientation": "HORIZONTAL", "TableContextTimeStampAfterTable": "{35251=Born: September 25, 1980 in Atlanta, GA, 138612=Copyright \u00a9 2014 Apple Inc. All rights reserved.}", "lastModified": "Sat, 01 Aug 2015 03:29:15 GMT", "textBeforeTable": "View In iTunes Paperwork (Deluxe Version) 5. View In iTunes King 4. View In iTunes No Mercy (Deluxe Version) 3. View In iTunes Trouble Man: Heavy Is the Head (Deluxe Version)", "textAfterTable": "Listeners Also Bought Jesus Piece The Game View In iTunes Life Is Good Nas View In iTunes Quality Street Music DJ Drama View In iTunes", "hasKeyColumn": true, "keyColumnIndex": 1, "headerRowIndex": 0}