{"relation": [["", "1", "2", "3", "4", "5", "6", "7", "8", "9", "10"], ["Name", "Mountain Voice", "Dembildey / Nomad Dance", "Mezhegey", "Chashpy-Hem / Chashpy River", "Artyy Sayir", "Bai-Taiga", "Ovyur Hadip", "Erge Chokka / Unneeded", "Ergim Syaryym / Song of Hope", "Daglarym"], ["Album", "Spirits from Tuva", "Mother Earth! Father Sky!", "Mother Earth! Father Sky!", "Mother Earth! Father Sky!", "Mother Earth! Father Sky!", "Mother Earth! Father Sky!", "Mother Earth! Father Sky!", "Mother Earth! Father Sky!", "Mother Earth! Father Sky!", "Mother Earth! Father Sky!"], ["Time", "5:30", "6:02", "4:21", "6:28", "5:43", "4:22", "3:56", "6:27", "4:33", "3:00"], ["Price", "\u20ac0.99", "\u20ac0.99", "\u20ac0.99", "\u20ac0.99", "\u20ac0.99", "\u20ac0.99", "\u20ac0.99", "\u20ac0.99", "\u20ac0.99", "\u20ac0.99"], ["", "View In iTunes", "View In iTunes", "View In iTunes", "View In iTunes", "View In iTunes", "View In iTunes", "View In iTunes", "View In iTunes", "View In iTunes", "View In iTunes"]], "pageTitle": "iTunes - Music - Mother Earth! Father Sky! by Huun-Huur-Tu", "title": "", "url": "https://itunes.apple.com/ie/album/erge-chokka-unneeded/id285221574?i=285221600", "hasHeader": true, "headerPosition": "FIRST_ROW", "tableType": "RELATION", "tableNum": 2, "s3Link": "common-crawl/crawl-data/CC-MAIN-2015-32/segments/1438042988061.16/warc/CC-MAIN-20150728002308-00091-ip-10-236-191-2.ec2.internal.warc.gz", "recordEndOffset": 861277243, "recordOffset": 861249571, "tableOrientation": "HORIZONTAL", "TableContextTimeStampAfterTable": "{115671=Shop at the Apple Online Store, call 1800 92 38 98 or find a retailer., 116529=Copyright \u00a9 2014 Apple Inc. All rights reserved.}", "lastModified": "Fri, 31 Jul 2015 07:35:12 GMT", "textBeforeTable": "View In iTunes If I'd Been Born an Eagle 5. View In iTunes Mother Earth! Father Sky! 4. View In iTunes Fly, Fly My Sadness 3.", "textAfterTable": "Listeners Also Bought Fly, Fly My Sadness Angelite, Moscow Art Trio & Huun-Huur-Tu View In iTunes Legend (with Huun-Huur-Tu & the Moscow Art Trio) The Bulgarian Voices - Angelite View In iTunes", "hasKeyColumn": true, "keyColumnIndex": 1, "headerRowIndex": 0}