{"relation": [["Title", "Test Server Thread", "Cache any function (with its arguments)", "Cache Any Function"], ["Author", "adamlofts", "bkroeze", "jeffwheeler"], ["Tags", "thread test", "cache function threading threads thread", "cache function threading threads thread"], ["Publication date", "June 17, 2009, 11:43 a.m.", "April 25, 2007, 4:31 p.m.", "March 14, 2007, 11:52 p.m."], ["Rating", "+2", "+6", "+10"]], "pageTitle": "djangosnippets: Tag \"thread\"", "title": "", "url": "https://djangosnippets.org/tags/thread/", "hasHeader": true, "headerPosition": "FIRST_ROW", "tableType": "RELATION", "tableNum": 0, "s3Link": "common-crawl/crawl-data/CC-MAIN-2015-32/segments/1438042987127.36/warc/CC-MAIN-20150728002307-00265-ip-10-236-191-2.ec2.internal.warc.gz", "recordEndOffset": 859641215, "recordOffset": 859633343, "tableOrientation": "HORIZONTAL", "textBeforeTable": "Tag \"thread\" Most bookmarked Highest rated By tag By language By author All snippets Add a snippet djangosnippets Login", "textAfterTable": "\u00a0\u00a0 3 snippets posted so far. Feed of snippets tagged with 'thread' Written by various people. Hosted by Heroku, powered by Django About | FAQ | Terms of service | Legal notices", "hasKeyColumn": true, "keyColumnIndex": 0, "headerRowIndex": 0}