{"relation": [["", "1", "2", "3", "4", "5", "6", "7", "8", "9", "10"], ["Name", "Too Late", "Too Late", "Tomorrow Night", "Tomorrow Night", "Curiosity", "In My Arms Again", "Karen", "Feel the Way That I Do", "She Satisfies", "Your Very Eyes"], ["Album", "SHOES Best", "Present Tense / Tongue Twister", "SHOES Best", "Present Tense / Tongue Twister", "Boomerang/Shoes On Ice", "Present Tense / Tongue Twister", "Present Tense / Tongue Twister", "Stolen Wishes", "Present Tense / Tongue Twister", "Present Tense / Tongue Twister"], ["Time", "2:44", "2:47", "2:58", "2:58", "3:28", "4:07", "2:48", "3:39", "3:05", "3:10"], ["Price", "$0.99", "$0.99", "$0.99", "$0.99", "$0.99", "$0.99", "$0.99", "$0.99", "$0.99", "$0.99"], ["", "View In iTunes", "View In iTunes", "View In iTunes", "View In iTunes", "View In iTunes", "View In iTunes", "View In iTunes", "View In iTunes", "View In iTunes", "View In iTunes"]], "pageTitle": "iTunes - Music - SHOES Best by Shoes", "title": "", "url": "https://itunes.apple.com/us/album/karen/id62979702?i=62979607", "hasHeader": true, "headerPosition": "FIRST_ROW", "tableType": "RELATION", "tableNum": 2, "s3Link": "common-crawl/crawl-data/CC-MAIN-2015-32/segments/1438042988458.74/warc/CC-MAIN-20150728002308-00175-ip-10-236-191-2.ec2.internal.warc.gz", "recordEndOffset": 874727019, "recordOffset": 874700794, "tableOrientation": "HORIZONTAL", "TableContextTimeStampAfterTable": "{44050=Formed: 1975 in Zion, IL, 142849=Copyright \u00a9 2014 Apple Inc. All rights reserved.}", "lastModified": "Sat, 01 Aug 2015 04:14:33 GMT", "textBeforeTable": "View In iTunes Boomerang/Shoes On Ice 5. View In iTunes Ignition 4. View In iTunes Black Vinyl Shoes 3. View In iTunes SHOES Best 2.", "textAfterTable": "Listeners Also Bought Shut Up and Kiss Me! Stuck on Broadway View In iTunes Cantilever Jeff Murphy View In iTunes Balance Balance View In iTunes", "hasKeyColumn": true, "keyColumnIndex": 1, "headerRowIndex": 0}