{"relation": [["", "1", "2", "3", "4", "5", "6", "7", "8", "9", "10"], ["Name", "Look My Way", "Moment of Truth", "Cut Off", "Temptation or Restraint", "Waste of Time", "False Threats", "Pushin' Me", "Walk Away", "Our Family", "Lesson of Life"], ["Album", "Look My Way", "Look My Way", "Look My Way", "Look My Way", "Look My Way", "Look My Way", "Look My Way", "Look My Way", "Look My Way", "Look My Way"], ["Time", "2:48", "1:38", "2:37", "1:20", "3:04", "2:14", "2:07", "0:58", "2:12", "3:19"], ["Price", "0,99 \u20ac", "0,99 \u20ac", "0,99 \u20ac", "0,99 \u20ac", "0,99 \u20ac", "0,99 \u20ac", "0,99 \u20ac", "0,99 \u20ac", "0,99 \u20ac", "0,99 \u20ac"], ["", "View In iTunes", "View In iTunes", "View In iTunes", "View In iTunes", "View In iTunes", "View In iTunes", "View In iTunes", "View In iTunes", "View In iTunes", "View In iTunes"]], "pageTitle": "iTunes - Music - Hold It Down by Madball", "title": "", "url": "https://itunes.apple.com/ee/album/hold-it-down/id271943153?i=271943158", "hasHeader": true, "headerPosition": "FIRST_ROW", "tableType": "RELATION", "tableNum": 2, "s3Link": "common-crawl/crawl-data/CC-MAIN-2015-32/segments/1438042988061.16/warc/CC-MAIN-20150728002308-00158-ip-10-236-191-2.ec2.internal.warc.gz", "recordEndOffset": 870017727, "recordOffset": 869991938, "tableOrientation": "HORIZONTAL", "TableContextTimeStampAfterTable": "{118980=Autori\u00f5igus \u00a9 2014, Apple Inc. K\u00f5ik \u00f5igused on reserveeritud., 25470=Formed: 1989 in New York, NY}", "lastModified": "Fri, 31 Jul 2015 07:58:41 GMT", "textBeforeTable": "View In iTunes Empire 5. View In iTunes N.Y.H.C. - EP 4. View In iTunes Hold It Down 3. View In iTunes The Best of Madball 2.", "textAfterTable": "Listeners Also Bought No Remorse - EP Naysayer View In iTunes What It Meant: The Complete Discography Judge View In iTunes Somery Descendents View In iTunes", "hasKeyColumn": true, "keyColumnIndex": 1, "headerRowIndex": 0}