{"relation": [["", "1", "2", "3", "4", "5", "6", "7", "8", "9", "10"], ["Name", "New Roll", "A Weirding Away", "Rogue's Yarn", "Left Handy Man Handle", "Paraphrase", "Big Spider", "Grandfather Claws", "Betwixt", "Shhmna", "Wild Notes"], ["Album", "Night Terror", "Night Terror", "Night Terror", "Night Terror", "Night Terror", "Night Terror", "Night Terror", "Night Terror", "Night Terror", "Night Terror"], ["Time", "5:42", "3:43", "4:22", "2:31", "3:52", "2:29", "3:19", "2:53", "3:38", "3:26"], ["Price", "$0.99", "$0.99", "$0.99", "$0.99", "$0.99", "$0.99", "$0.99", "$0.99", "$0.99", "$0.99"], ["", "View In iTunes", "View In iTunes", "View In iTunes", "View In iTunes", "View In iTunes", "View In iTunes", "View In iTunes", "View In iTunes", "View In iTunes", "View In iTunes"]], "pageTitle": "iTunes - Music - Sleepwalking Sailors by Helms Alee", "title": "", "url": "https://itunes.apple.com/us/album/sleepwalking-sailors/id795470218?app=itunes", "hasHeader": true, "headerPosition": "FIRST_ROW", "tableType": "RELATION", "tableNum": 2, "s3Link": "common-crawl/crawl-data/CC-MAIN-2015-32/segments/1438042988458.74/warc/CC-MAIN-20150728002308-00271-ip-10-236-191-2.ec2.internal.warc.gz", "recordEndOffset": 881122483, "recordOffset": 881096288, "tableOrientation": "HORIZONTAL", "TableContextTimeStampAfterTable": "{23834=Formed: 2007 in Seattle, WA, 122956=Copyright \u00a9 2014 Apple Inc. All rights reserved.}", "lastModified": "Sat, 01 Aug 2015 03:31:50 GMT", "textBeforeTable": "View In iTunes Lionize/Truly [Digital 45] 5. View In iTunes Helms Alee / Young Widows - Split - EP 4. View In iTunes Night Terror 3.", "textAfterTable": "Listeners Also Bought Take My Bones Away - Single Baroness View In iTunes What We All Come to Need Pelican View In iTunes Led Zeppelin III (Remastered)", "hasKeyColumn": true, "keyColumnIndex": 1, "headerRowIndex": 0}