{"relation": [["Disc 1 Titles", "1. Harlem II", "2. Goin' To Las Vegas", "3. Love You", "4. Cool As Ice", "5. All Night Long", "6. Sister Ray Says", "7. Johnny Dance", "8. Space Blue", "9. Long Talk", "10. Speed Queen", "11. Chezazze", "12. Dreams", "13. All Night Long", "14. Sweetheart", "15. Scream and Shout"], ["Artist", "Suicide", "Suicide", "Suicide", "Suicide", "Suicide", "Suicide", "Suicide", "Suicide", "Suicide", "Suicide", "Suicide", "Suicide", "Suicide", "Suicide", "Suicide"], ["Length", "03:56", "04:15", "02:45", "03:19", "04:05", "04:25", "03:00", "01:46", "01:27", "02:27", "03:24", "02:09", "04:31", "04:44", "04:18"], ["File/Price", "MP3 - $0.98 M4A - $1.38 WAV - $1.78", "MP3 - $0.98 M4A - $1.38 WAV - $1.78", "MP3 - $0.98 M4A - $1.38 WAV - $1.78", "MP3 - $0.98 M4A - $1.38 WAV - $1.78", "MP3 - $0.98 M4A - $1.38 WAV - $1.78", "MP3 - $0.98 M4A - $1.38 WAV - $1.78", "MP3 - $0.98 M4A - $1.38 WAV - $1.78", "MP3 - $0.98 M4A - $1.38 WAV - $1.78", "MP3 - $0.98 M4A - $1.38 WAV - $1.78", "MP3 - $0.98 M4A - $1.38 WAV - $1.78", "MP3 - $0.98 M4A - $1.38 WAV - $1.78", "MP3 - $0.98 M4A - $1.38 WAV - $1.78", "MP3 - $0.98 M4A - $1.38 WAV - $1.78", "MP3 - $0.98 M4A - $1.38 WAV - $1.78", "MP3 - $0.98 M4A - $1.38 WAV - $1.78"], ["Buy", "", "", "", "", "", "", "", "", "", "", "", "", "", "", ""]], "pageTitle": "Suicide - Half Alive (MP3, M4A, WAV Download) - Amoeba Music", "title": "", "url": "http://www.amoeba.com/half-alive-suicide/albums/1712083/", "hasHeader": true, "headerPosition": "FIRST_ROW", "tableType": "RELATION", "tableNum": 0, "s3Link": "common-crawl/crawl-data/CC-MAIN-2015-32/segments/1438042988458.74/warc/CC-MAIN-20150728002308-00166-ip-10-236-191-2.ec2.internal.warc.gz", "recordEndOffset": 296717947, "recordOffset": 296700751, "tableOrientation": "HORIZONTAL", "TableContextTimeStampAfterTable": "{23498=Copyright \u00a9 2015 Amoeba, All Rights Reserved. Amoeba and the Amoeba Music mark and logo are trademarks of Amoeba Music Inc.}", "lastModified": "Sat, 01 Aug 2015 03:48:15 GMT", "textBeforeTable": "Track Listing WAV $14.98 M4A $12.48 MP3 $9.98 Suicide Half Alive Tweet Half Alive Home View More Dub Trio Lv (LP) 10 Ft. Ganja Plant 10 Deadly Shots Vol. II (CD) 10 Ft. Ganja Plant 10 Deadly Shots Vol.", "textAfterTable": "MP3 $9.98 M4A $12.48 WAV $14.98 User Reviews Overall Rating 0 Submissions RATE & REVIEW Who We Are Amoeblog Buy Sell Trade News & Contests Gift Certificates Contact Us Support & FAQ", "hasKeyColumn": true, "keyColumnIndex": 0, "headerRowIndex": 0}