{"relation": [["", "1", "2", "3", "4", "5", "6", "7", "8", "9", "10", "11", "12", "13", "14", "15", "16", "17", "18", "19", "20"], ["Name", "Bull and Butcher", "Believe It or Not", "Black Winow", "Blue Star", "Funky Town", "A Night On the Beach", "Crucial Love", "Lady Groove", "Glamour Night", "About Us", "Bounce Out Stop", "Guitarra Sospesa", "Give Me", "Mr. Mason", "Soave", "Cool Music for Cool People", "Long Love", "This Heaven", "Living Music", "Silver Cocktail"], ["Artist", "MF", "City Centre Ensemble", "Frank D", "Deep Selected", "Long Beach Grooves", "Deephouse 84", "Crucial Love", "Frank D & Co", "The Flyhigh Project", "Cool Jaques", "Florinda Project", "Alex Latino", "K. Grooves", "Chill Forever", "D Grooves", "K. Krown", "DJ Joseph B", "4th Sensation", "Modern Lounge Hereos", "Floor 21"], ["Time", "3:15", "3:14", "3:48", "3:47", "2:24", "3:20", "3:06", "3:14", "3:26", "4:04", "4:28", "2:54", "3:36", "5:52", "4:04", "4:06", "4:33", "3:18", "8:04", "3:58"], ["Price", "0,99 \u20ac", "0,99 \u20ac", "0,99 \u20ac", "0,99 \u20ac", "0,99 \u20ac", "0,99 \u20ac", "0,99 \u20ac", "0,99 \u20ac", "0,99 \u20ac", "0,99 \u20ac", "0,99 \u20ac", "0,99 \u20ac", "0,99 \u20ac", "0,99 \u20ac", "0,99 \u20ac", "0,99 \u20ac", "0,99 \u20ac", "0,99 \u20ac", "0,99 \u20ac", "0,99 \u20ac"], ["", "View In iTunes", "View In iTunes", "View In iTunes", "View In iTunes", "View In iTunes", "View In iTunes", "View In iTunes", "View In iTunes", "View In iTunes", "View In iTunes", "View In iTunes", "View In iTunes", "View In iTunes", "View In iTunes", "View In iTunes", "View In iTunes", "View In iTunes", "View In iTunes", "View In iTunes", "View In iTunes"]], "pageTitle": "iTunes - Music - Late Night Lounge Miami - 20 Tracks for a Perfect Night by Various Artists", "title": "", "url": "https://itunes.apple.com/gr/album/bull-and-butcher/id307267217?i=307267280", "hasHeader": true, "headerPosition": "FIRST_ROW", "tableType": "RELATION", "tableNum": 0, "s3Link": "common-crawl/crawl-data/CC-MAIN-2015-32/segments/1438042988458.74/warc/CC-MAIN-20150728002308-00251-ip-10-236-191-2.ec2.internal.warc.gz", "recordEndOffset": 872990687, "recordOffset": 872969633, "tableOrientation": "HORIZONTAL", "TableContextTimeStampAfterTable": "{88804=Copyright \u00a9 2014 Apple Inc. \u039c\u03b5 \u03b5\u03c0\u03b9\u03c6\u03cd\u03bb\u03b1\u03be\u03b7 \u03c0\u03b1\u03bd\u03c4\u03cc\u03c2 \u03b4\u03b9\u03ba\u03b1\u03b9\u03ce\u03bc\u03b1\u03c4\u03bf\u03c2.}", "lastModified": "Sat, 01 Aug 2015 05:00:37 GMT", "textBeforeTable": "Open iTunes to preview, buy and download music. Various Artists Late Night Lounge Miami - 20 Tracks for a Perfect Night iTunes for Mac + PC Do you already have iTunes? Click I Have iTunes to open it now. We are unable to find iTunes on your computer. To preview and buy music from Late Night Lounge Miami - 20 Tracks for a Perfect Night by Various Artists, download iTunes now. iTunes is the world's easiest way to organize and add to your digital media collection. iTunes Progress Indicator If iBooks doesn't open, click the iBooks app in your Dock. Opening the iBooks Store. Progress Indicator If iTunes doesn\u2019t open, click the iTunes", "textAfterTable": "20 Songs Listeners Also Bought Fashion Vibes, Vol. 2 Various Artists View In iTunes Jazzy Chill House, Vol. 1 Luxury Grooves View In iTunes", "hasKeyColumn": true, "keyColumnIndex": 1, "headerRowIndex": 0}