{"relation": [["Title", "Abbreviations used in Pages of Go Tournament Results", "A newsletter", "Anglo-Japanese Matches", "Alex Kent", "AGM Summary 2013", "Andrew Simons wins restarted Birmingham", "Adam Atkinson", "Alex Dinerchtein", "Alison Cross", "Arundel Tournament Results", "Alex Kent wins Goat Ornament", "Andrew Kay Interviewed at WAGC", "Andrew Kay 24th at WAGC", "Alex Kent Wins 44th Wessex", "Archivist", "Advice for Studying", "A disaster against the Turks...", "A Happy Partner", "Andrew Grant", "Anna Griffiths", "Alex Rix", "Accommodation at EYGC and BGC", "Andrew Simons wins Stacey Grand Prix for 2013:", "Andrew Kay Retains British Championship:", "Arundel: 2008", "AGM minutes", "Andrew Simons beats organiser to win Trigantius 2013:", "Andrew Simons wins Trigantius 2012:", "Andrew Kay wins Candidates':", "Andrew Kay wins Candidates' in Edinburgh:", "Andrew Simons wins tied Maidenhead-Hitachi:", "A repeat win against Croatia 3-1", "AGM 2014 Agenda", "AGM 2014 Papers", "A. Default Rules", "Archive: past Go events in the UK 2010"], ["Author", "Anonymous", "Tony Atkins", "Jon Diamond", "Jon Diamond", "Tony Atkins", "Tony Atkins", "Jon Diamond", "Jon Diamond", "Jon Diamond", "Tony Atkins", "Tony Atkins", "Tony Atkins", "Tony Atkins", "Tony Atkins", "Jon Diamond", "brianbrunswick", "Jon Diamond", "Tony Atkins", "Jon Diamond", "Jon Diamond", "Jon Diamond", "Tony Atkins", "Jon Diamond", "Tony Atkins", "Tony Atkins", "Jon Diamond", "Tony Atkins", "Tony Atkins", "Tony Atkins", "Tony Atkins", "Tony Atkins", "Jon Diamond", "Jon Diamond", "Jon Diamond", "Anonymous", "Tony Atkins"], ["Last update", "Wednesday, 2 January, 2013 - 19:38", "Friday, 4 January, 2013 - 13:03", "Friday, 4 January, 2013 - 15:19", "Wednesday, 27 March, 2013 - 11:37", "Monday, 8 April, 2013 - 13:19", "Sunday, 21 April, 2013 - 12:45", "Sunday, 19 May, 2013 - 17:17", "Monday, 20 May, 2013 - 10:45", "Monday, 20 May, 2013 - 11:23", "Tuesday, 4 June, 2013 - 13:07", "Sunday, 7 July, 2013 - 20:05", "Wednesday, 4 September, 2013 - 16:07", "Wednesday, 4 September, 2013 - 16:19", "Monday, 28 October, 2013 - 23:21", "Friday, 1 November, 2013 - 10:16", "Saturday, 23 November, 2013 - 11:34", "Sunday, 8 December, 2013 - 20:14", "Tuesday, 31 December, 2013 - 11:48", "Thursday, 2 January, 2014 - 11:27", "Friday, 31 January, 2014 - 11:30", "Friday, 31 January, 2014 - 17:32", "Tuesday, 4 February, 2014 - 13:41", "Tuesday, 11 February, 2014 - 12:08", "Tuesday, 11 February, 2014 - 12:12", "Wednesday, 12 February, 2014 - 13:36", "Thursday, 13 February, 2014 - 14:57", "Friday, 14 February, 2014 - 11:08", "Friday, 14 February, 2014 - 11:08", "Friday, 14 February, 2014 - 11:43", "Friday, 14 February, 2014 - 11:44", "Friday, 14 February, 2014 - 12:24", "Friday, 21 February, 2014 - 20:38", "Thursday, 27 February, 2014 - 12:09", "Thursday, 27 February, 2014 - 13:44", "Tuesday, 11 March, 2014 - 18:25", "Wednesday, 12 March, 2014 - 14:53"]], "pageTitle": "Glossary | British Go Association", "title": "", "url": "http://www.britgo.org/glossary?order=changed&sort=asc&page=3", "hasHeader": true, "headerPosition": "FIRST_ROW", "tableType": "RELATION", "tableNum": 0, "s3Link": "common-crawl/crawl-data/CC-MAIN-2015-32/segments/1438042988061.16/warc/CC-MAIN-20150728002308-00071-ip-10-236-191-2.ec2.internal.warc.gz", "recordEndOffset": 344232792, "recordOffset": 344224590, "tableOrientation": "HORIZONTAL", "lastModified": "Fri, 31 Jul 2015 07:27:16 GMT", "textBeforeTable": "| 7 (3) | 6 (8) | 5 (4) | 4 (5) | 3 (14) | 2 (28) | 1 (21) | ( (1) | (10) (2) Glossary Home Forum Notifications Enhancements needed Should we have a public membership list? Forum Listings", "textAfterTable": "\u00ab first \u2039 previous 1 2 3 4 5 6 next \u203a last \u00bb", "hasKeyColumn": true, "keyColumnIndex": 0, "headerRowIndex": 0}