{"relation": [["Title", "Club Information", "Stop Press", "Chairman's Bytes - April-June 2013", "Consecutive Sums", "CAS Roadblock", "Repairing the HP9866A printer - Part 1", "HP Prime", "Running hp50's Around the Clock", "Number Chains - A Challenge", "HP Handhelds History - the hp 40gs & upgraded HP48gII"], ["Subject", "", "", "General", "HP50G", "HP50G", "HP9866A", "Prime", "HP50G", "HP50G", "HP40GS HP48gII"], ["Author", "", "", "W\u0142odek Mier-J\u0119drzejowicz", "Jeremy Hawdon", "Bill Butler", "Tony Duell", "Bruce Horrocks", "Bill Butler", "Jeremy Hawdon", "W\u0142odek Mier-J\u0119drzejowicz"], ["Page", "V32N2P2", "V32N2P2", "V32N2P3", "V32N2P4", "V32N2P5", "V32N2P6", "V32N2P14", "V32N2P22", "V32N2P22", "V32N2P23"]], "pageTitle": "HPCC Magazine: Datafile V32", "title": "", "url": "http://www.hpcc.org/datafile/datafilev32.html", "hasHeader": true, "headerPosition": "FIRST_ROW", "tableType": "RELATION", "tableNum": 9, "s3Link": "common-crawl/crawl-data/CC-MAIN-2015-32/segments/1438042988061.16/warc/CC-MAIN-20150728002308-00273-ip-10-236-191-2.ec2.internal.warc.gz", "recordEndOffset": 492645017, "recordOffset": 492636815, "tableOrientation": "HORIZONTAL", "lastModified": "Mon, 09 Mar 2015 20:49:04 GMT", "textBeforeTable": "V32 N4\u00a0 \u00a0October/November/December 2013 \u00a0 V32N1 V32N2 V32N3 V32N4 \u00a0 \u00a0 V1 V2 V3 V4 V5 V6 V7 V8 V9 V10 V11 V12 V13 V14 V15 V16 V17 V18 V19 V20 V21 V22 V23 V24 V25 V26 V27 V28 V29 V30 V31 V32 V33 V34 General \u00a0 \u00a0", "textAfterTable": "Prime Time [Wasting] HP Prime John Olwoch V32N4P28 Cartoon General XKCD.com V32N4P30 Prime Time [Setting] HP Prime Joe Horn V32N4P30 HP Handhelds History - the HP 10s HP10S W\u0142odek Mier-J\u0119drzejowicz V32N4P31 For Sale and Wanted General W\u0142odek Mier-J\u0119drzejowicz V32N4P31 \u00a0July/August/September 2013 V32 N3\u00a0 Title Subject Author Page Club Information \u00a0 \u00a0 V32N3P2 Stop Press \u00a0 \u00a0 V32N3P2 Editorial General Bruce Horrocks V32N3P3 Members' Letters - Current Discussion of HPCC future General Karl-Ludwig Butte V32N3P4 HHC 2013 Announcement General Bruce Horrocks V32N3P5 Chairman's Bytes - July to September 2013 General W\u0142odek Mier-J\u0119drzejowicz V32N3P6 Repairing the HP9866A printer - Part 2 HP9866A Tony Duell V32N3P7 Finding Pythagorean Triads HP50G Jeremy Hawdon V32N3P15 DIVIS and FACTOR for the HP48 HP48 Jeremy Hawdon V32N3P17 Some Thoughts on Number Chains HP50G Philip Belben V32N3P18 FINZ=FIN updated for the 41C HP-41C Tony Hutchins V32N3P20 HP Handhelds History - the HP 35s HP35S W\u0142odek Mier-J\u0119drzejowicz V32N3P27 \u00a0April/May/June 2013 V32 N2\u00a0", "hasKeyColumn": true, "keyColumnIndex": 0, "headerRowIndex": 0}