{"relation": [["", "", "", "", "", "", "", "", "", "", "", "", "", "", "", "", "", "", "", "", "", "", "", "", "", "", "", "", "", "", "", "", "", ">>", "", "", "", "", "", "", "", "", "", "", "", "", "", "", "", "", "", "", "", "", "", "", "", "", "", "", "", "", "", "", "", "", "", "", "", "", "", "", "", "", "", "", "", "", "", "", "", "", "", "", "", ""], ["", "1.", "2.", "3.", "4.", "6.", "9.", "27.", "29.", "5.", "7.", "8.", "10.", "11.", "12.", "15.", "13.", "14.", "49.", "53.", "62.", "56.", "16.", "17.", "18.", "19.", "22.", "23.", "25.", "26.", "33.", "34.", "35.", "37.", "61.", "39.", "40.", "41.", "43.", "45.", "46.", "47.", "55.", "42.", "28.", "20.", "21.", "30.", "31.", "32.", "51.", "52.", "48.", "24.", "36.", "38.", "44.", "50.", "54.", "57.", "58.", "59.", "60.", "63.", "64.", "65.", "66.", "67.", "70.", "74.", "78.", "79.", "73.", "72.", "76.", "77.", "80.", "81.", "82.", "83.", "84.", "85.", "68.", "69.", "75.", "71."], ["Date", "Jan 31, 12:29", "Jan 31, 12:53", "Jan 31, 12:59", "Jan 31, 13:01", "Jan 31, 13:13", "Jan 31, 13:23", "Jan 31, 18:23", "Jan 31, 18:34", "Jan 31, 13:12", "Jan 31, 13:15", "Jan 31, 13:21", "Jan 31, 13:36", "Jan 31, 14:13", "Jan 31, 14:14", "Jan 31, 15:16", "Jan 31, 14:14", "Jan 31, 14:59", "Feb 1, 03:20", "Feb 1, 06:55", "Feb 1, 14:45", "Feb 1, 07:52", "Jan 31, 15:16", "Jan 31, 15:30", "Jan 31, 16:23", "Jan 31, 16:39", "Jan 31, 17:27", "Jan 31, 17:31", "Jan 31, 18:01", "Jan 31, 18:17", "Jan 31, 20:01", "Jan 31, 20:18", "Jan 31, 20:47", "Jan 31, 21:20", "Feb 1, 14:39", "Jan 31, 21:48", "Jan 31, 21:59", "Jan 31, 22:13", "Jan 31, 22:36", "Jan 31, 23:21", "Jan 31, 23:40", "Feb 1, 01:45", "Feb 1, 07:47", "Jan 31, 22:24", "Jan 31, 18:24", "Jan 31, 17:14", "Jan 31, 17:22", "Jan 31, 19:13", "Jan 31, 19:49", "Jan 31, 19:59", "Feb 1, 04:00", "Feb 1, 04:44", "Feb 1, 03:01", "Jan 31, 17:48", "Jan 31, 20:56", "Jan 31, 21:32", "Jan 31, 23:18", "Feb 1, 03:37", "Feb 1, 06:59", "Feb 1, 07:56", "Feb 1, 08:04", "Feb 1, 09:32", "Feb 1, 13:36", "Feb 1, 15:16", "Feb 1, 16:32", "Feb 1, 17:21", "Feb 1, 18:18", "Feb 1, 19:34", "Feb 1, 22:54", "Feb 2, 01:36", "Feb 2, 05:41", "Feb 2, 10:07", "Feb 2, 01:33", "Feb 2, 01:27", "Feb 2, 01:49", "Feb 2, 02:56", "Feb 2, 12:14", "Feb 2, 13:03", "Feb 2, 13:53", "Feb 2, 23:51", "Feb 7, 16:06", "Feb 7, 16:12", "Feb 1, 22:21", "Feb 1, 22:40", "Feb 2, 01:39", "Feb 2, 01:21"], ["Subject", "anyone play this lately?", "Re: anyone play this lately?", "Re: anyone play this lately?", "Re: anyone play this lately?", "Re: anyone play this lately?", "Re: anyone play this lately?", "Re: anyone play this lately?", "Re: anyone play this lately?", "Re: anyone play this lately?", "Doom 3", "Re: Doom 3", "No subject", "Far Cry vs. Half-Life2", "Re: No subject", "Re: No subject", "Re: No subject", "Re: No subject", "Re: JosephBlowski", "Re: JosephBlowski", "Re: JosephBlowski", "Re: No subject", "No subject", "Re: No subject", "Re: No subject", "Re: No subject", "Re: No subject", "Re: No subject", "Re: No subject", "Re: No subject", "Re: No subject", "Re: No subject", "Re: No subject", "Re: No subject", "Re: No subject", "Re: No subject", "Re: No subject", "Re: No subject", "Re: No subject", "Re: No subject", "Re: No subject", "WOW...", "Re: No subject", "Re: No subject", "Re: No subject", "no storyline", "Re: no storyline", "Re: no storyline", "Re: no storyline", "Re: no storyline", "Re: no storyline", "Re: no storyline", "Re: Kajetan", "Re: no storyline", "7 years to make? ha", "Near Whimper", "Wow", "Re: Wow", "Re: Wow", "Re: Wow", "Re: Wow", "Re: Wow", "The truth about HalfLife2", "Re: The truth about HalfLife2", "That's a load of shit", "Re: That's a load of shit", "Re: That's a load of shit", "Re: That's a load of shit", "Re: That's a load of shit", "Re: That's a load of shit", "Re: That's a load of shit", "Re: That's a load of shit", "Re: That's a load of shit", "Re: The truth about HalfLife2", "Scottish Martial Arts & Beamer = ...", "Re: Scottish Martial Arts & Beamer = ...", "Re: Scottish Martial Arts & Beamer = ...", "Re: Scottish Martial Arts & Beamer = ...", "Re: Scottish Martial Arts & Beamer = ...", "Re: Scottish Martial Arts & Beamer = ...", "Re: Scottish Martial Arts & Beamer = ...", "Re: Scottish Martial Arts & Beamer = ...", "Re: Wow", "heh...", "Re: Wow", "Re: Wow"], ["Author", "Wildone", "Brian", "ZigZang", "sponge", "Koblizek", "Old_Geezer", "Awesome Spume", "Scottish Martial Arts", "Old_Geezer", "PanzerMeyer", "nin", "Xero", "Zephalephelah", "vacs", "Xero", "Warskull", "JosephBlowski", "Zephalephelah", "JosephBlowski", "famished", "vacs", "famished", "mittens", "QWL2", "famished", "DPmaster", "Mega Fantasy Sci-Fi PostApocalyptic MMORTRPFPS 9000", "vacs", "Squirmer", "Mega Fantasy Sci-Fi PostApocalyptic MMORTRPFPS 9000", "Panick", "Beamer", "Beaner", "famished", "Mega Fantasy Sci-Fi PostApocalyptic MMORTRPFPS 9000", "Scottish Martial Arts", "Beamer", "Scottish Martial Arts", "Beaner", "Beamer", "BFSoLo.", "vacs", "kanniballl", "Scottish Martial Arts", "Mega Fantasy Sci-Fi PostApocalyptic MMORTRPFPS 9000", "StaTik", "Kajetan", "Ihya", "sponge", "Tango", "Drax", "Zephalephelah", "Beamer", "Tim", "Camaro76", "Creston", "Mega Fantasy Sci-Fi PostApocalyptic MMORTRPFPS 9000", "JosephBlowski", "Ihya", "vacs", "Beamer", "Zephalephelah", "Beamer", "Zephalephelah", "famished", "Beamer", "Zephalephelah", "Beamer", "Scottish Martial Arts", "famished", "Beamer", "Scottish Martial Arts", "Scottish Martial Arts", "Zephalephelah", "Old_Geezer", "Scottish Martial Arts", "Old_Geezer", "Scottish Martial Arts", "Old_Geezer", "Xenos Overdrive", "Xenos Overdrive", "Creston", "Zephalephelah", "Scottish Martial Arts", "Scottish Martial Arts"]], "pageTitle": "Far Cry Patch - Blue's News Comments", "title": "", "url": "http://www.bluesnews.com/cgi-bin/board.pl?action=viewthread&boardid=1&threadid=54467&id=228693&view=threads", "hasHeader": true, "headerPosition": "FIRST_ROW", "tableType": "RELATION", "tableNum": 20, "s3Link": "common-crawl/crawl-data/CC-MAIN-2015-32/segments/1438042988061.16/warc/CC-MAIN-20150728002308-00212-ip-10-236-191-2.ec2.internal.warc.gz", "recordEndOffset": 334003378, "recordOffset": 333986984, "tableOrientation": "HORIZONTAL", "TableContextTimeStampAfterTable": "{96989=News CGI copyright \u00a9 1999-2015 James \"furn\" Furness & Blue's News. All rights reserved., 97192=Chatbear v1.4.0/blue++: Page generated 31 July 2015, 03:53. Chatbear Announcements., 95074=Copyright \u00a9 1996-2015 Stephen Heaslip. All rights reserved. All trademarks are properties of their respective owners.}", "textBeforeTable": "Worthplaying. GameSpot DLX (registration required), and Gamer's Hell, Gameguru Mania, FileShack (registration required), FileFront, Boomtown (registration required), ActionTrip, 3D Gamers, A new patch is now available for Far Cry, updating Crytek's first-person shooter to version 1.31 addressing some multiplayer issues. The 9 MB download is available on [Jan 31, 2005, 1:25 pm ET] - Share - Viewing Comments Far Cry Patch --> Blue's News Favorite! Join Blue's News! Get TMNF Client Status: < ! --#include virtual=\"/inserts/tmfstatus.inc\" -- > / 30 players TrackMania Server Regularly scheduled events \u00a009/18 Harrisburg, PA Upcoming one-time events:", "textAfterTable": "76. Feb 2, 01:49 \u00a0\u00a0\u00a0\u00a0\u00a0Scottish Martial Arts & Beamer = ... Zephalephelah \u00a0 77. Feb 2, 02:56 \u00a0\u00a0\u00a0\u00a0\u00a0\u00a0Re: Scottish Martial Arts & Beamer = ... Old_Geezer \u00a0 80. Feb 2, 12:14 \u00a0\u00a0\u00a0\u00a0\u00a0\u00a0Re: Scottish Martial Arts & Beamer = ... Scottish Martial Arts \u00a0 81. Feb 2, 13:03 \u00a0\u00a0\u00a0\u00a0\u00a0\u00a0\u00a0Re: Scottish Martial Arts & Beamer = ... Old_Geezer \u00a0 82. Feb 2, 13:53 \u00a0\u00a0\u00a0\u00a0\u00a0\u00a0\u00a0\u00a0Re: Scottish Martial Arts & Beamer = ... Scottish Martial Arts \u00a0 83. Feb 2, 23:51 \u00a0\u00a0\u00a0\u00a0\u00a0\u00a0\u00a0\u00a0\u00a0", "hasKeyColumn": true, "keyColumnIndex": 3, "headerRowIndex": 0}