{"relation": [["", "1", "2", "3", "4", "5", "6", "7", "8", "9", "10"], ["Name", "CleanSwagga", "Execute (Original Mix)", "X Rated (Original Mix)", "CleanCalypso", "Deviance (Original Mix)", "Ohhh Nooo (Original Mix)", "The Underground (Original Mix)", "8 Bit Superhero (Original Mix)", "Sleepless (Original Mix)", "Sexism (Original Mix)"], ["Album", "Swagga / Invaderz - Single", "X Rated", "X Rated", "Boom EP", "X Rated", "X Rated", "X Rated", "X Rated", "X Rated", "X Rated"], ["Time", "5:32", "4:06", "4:25", "3:43", "4:32", "4:54", "4:56", "4:56", "5:23", "4:13"], ["Price", "$0.99", "$0.99", "$0.99", "$0.99", "$0.99", "$0.99", "$0.99", "$0.99", "$0.99", "$0.99"], ["", "View In iTunes", "View In iTunes", "View In iTunes", "View In iTunes", "View In iTunes", "View In iTunes", "View In iTunes", "View In iTunes", "View In iTunes", "View In iTunes"]], "pageTitle": "iTunes - Music - Boom / Swagga (Remixes) by Excision & Datsik", "title": "", "url": "https://itunes.apple.com/ca/album/boom-skism-remix/id376184198?i=376184220", "hasHeader": true, "headerPosition": "FIRST_ROW", "tableType": "RELATION", "tableNum": 2, "s3Link": "common-crawl/crawl-data/CC-MAIN-2015-32/segments/1438042988061.16/warc/CC-MAIN-20150728002308-00339-ip-10-236-191-2.ec2.internal.warc.gz", "recordEndOffset": 862860911, "recordOffset": 862835874, "tableOrientation": "HORIZONTAL", "TableContextTimeStampAfterTable": "{102864=Copyright \u00a9 2014 Apple Inc. All rights reserved.}", "lastModified": "Fri, 31 Jul 2015 08:16:55 GMT", "textBeforeTable": "View In iTunes Yin Yang / Obvious 5. View In iTunes X Rated (The Remixes) 4. View In iTunes Codename X 3. View In iTunes Boom EP", "textAfterTable": "Listeners Also Bought Boom EP Excision, Datsik & Flux Pavilion View In iTunes Various EP Various Artists View In iTunes Penamana - EP Original Sin & Taxman View In iTunes", "hasKeyColumn": true, "keyColumnIndex": 1, "headerRowIndex": 0}